drb_impl_wmts/__init__.py
drb_impl_wmts/_version.py
drb_impl_wmts/cortex.yml
drb_impl_wmts/exceptions.py
drb_impl_wmts/factory.py
drb_impl_wmts/wmts_nodes.py
drb_impl_wmts-1.0.0.data/data/requirements.txt
drb_impl_wmts-1.0.0.dist-info/METADATA
drb_impl_wmts-1.0.0.dist-info/WHEEL
drb_impl_wmts-1.0.0.dist-info/entry_points.txt
drb_impl_wmts-1.0.0.dist-info/top_level.txt
drb_impl_wmts-1.0.0.dist-info/RECORD
