Metadata-Version: 2.1
Name: drb-impl-wmts
Version: 1.0.0
Summary: DRB wmts OGC Service implementation
Home-page: https://gitlab.com/drb-python/impl/wmts
Author: GAEL Systems
Author-email: drb-python@gael.fr
License: UNKNOWN
Platform: UNKNOWN
Classifier: Programming Language :: Python :: 3.8
Classifier: License :: OSI Approved :: Apache Software License
Classifier: Operating System :: OS Independent
Requires-Python: >=3.8
Requires-Dist: drb-impl-wXs (<1.1.0,>=1.0.3)
